aiolifecycle/__init__.py
aiolifecycle/exceptions.py
aiolifecycle/handlers.py
aiolifecycle/py.typed
aiolifecycle/tests/__init__.py
aiolifecycle/tests/test_handler.py
aiolifecycle/tests/handlers/basic_order.py
aiolifecycle/tests/handlers/resource_chaining.py
aiolifecycle/tests/handlers/resource_cycle.py
aiolifecycle/tests/handlers/resource_cycle_context_reset.py
aiolifecycle/tests/handlers/resource_init_failure.py
aiolifecycle-0.1.8.dist-info/LICENSE.md
aiolifecycle-0.1.8.dist-info/METADATA
aiolifecycle-0.1.8.dist-info/WHEEL
aiolifecycle-0.1.8.dist-info/entry_points.txt
aiolifecycle-0.1.8.dist-info/top_level.txt
aiolifecycle-0.1.8.dist-info/RECORD
