Metadata-Version: 2.1
Name: aiolifecycle
Version: 0.1.8
Summary: Micro-framework to effectively run asyncio functions in synchronous contexts
Home-page: UNKNOWN
License: Apache License 2.0
Platform: UNKNOWN
Classifier: Programming Language :: Python :: 3
License-File: LICENSE.md
Requires-Dist: typing-extensions
Provides-Extra: test
Requires-Dist: pre-commit ; extra == 'test'
Requires-Dist: pytest (>=7.1.0) ; extra == 'test'
Requires-Dist: pytest-asyncio ; extra == 'test'
Requires-Dist: mypy ; extra == 'test'
Requires-Dist: isort ; extra == 'test'
Requires-Dist: autopep8 ; extra == 'test'
Requires-Dist: flake8 ; extra == 'test'
